dora_magma/Magma/.git
dora_magma/Magma/.gitignore
dora_magma/Magma/CODE_OF_CONDUCT.md
dora_magma/Magma/LICENSE
dora_magma/Magma/README.md
dora_magma/Magma/SECURITY.md
dora_magma/Magma/SUPPORT.md
dora_magma/Magma/agents/game_agent/app.py
dora_magma/Magma/agents/game_agent/frozen_lake/app.py
dora_magma/Magma/agents/libero/README.md
dora_magma/Magma/agents/libero/eval_magma_libero.py
dora_magma/Magma/agents/libero/libero_env_utils.py
dora_magma/Magma/agents/libero/libero_magma_utils.py
dora_magma/Magma/agents/libero/requirements.txt
dora_magma/Magma/agents/robot_traj/app.py
dora_magma/Magma/agents/robot_traj/app.pyi
dora_magma/Magma/agents/robot_traj/sample.png
dora_magma/Magma/agents/robot_traj/utils/visualizer.py
dora_magma/Magma/agents/ui_agent/app.py
dora_magma/Magma/agents/ui_agent/util/__init__.py
dora_magma/Magma/agents/ui_agent/util/arial.ttf
dora_magma/Magma/agents/ui_agent/util/box_annotator.py
dora_magma/Magma/agents/ui_agent/util/omniparser.py
dora_magma/Magma/agents/ui_agent/util/process_utils.py
dora_magma/Magma/agents/ui_agent/util/som.py
dora_magma/Magma/agents/ui_agent/util/utils.py
dora_magma/Magma/assets/images/apple.png
dora_magma/Magma/assets/images/magma_game.png
dora_magma/Magma/assets/images/magma_intro_fig.png
dora_magma/Magma/assets/images/magma_logo.jpg
dora_magma/Magma/assets/images/magma_pt_v3.png
dora_magma/Magma/assets/images/magma_teaser.png
dora_magma/Magma/assets/images/som_flatten.png
dora_magma/Magma/assets/images/tom_fig.png
dora_magma/Magma/assets/images/ui_agent_example.png
dora_magma/Magma/assets/videos/robot_pick_up_chip_bag.mp4
dora_magma/Magma/assets/videos/robot_push_chip_bag_to_left_edge_of_table.mp4
dora_magma/Magma/assets/videos/tom_orig_sample.mp4
dora_magma/Magma/assets/videos/ui_mobile.mp4
dora_magma/Magma/data/__init__.py
dora_magma/Magma/data/conversations.py
dora_magma/Magma/data/data_collator.py
dora_magma/Magma/data/data_item.py
dora_magma/Magma/data/dataset.py
dora_magma/Magma/data/ego4d/__init__.py
dora_magma-0.1.0.dist-info/METADATA
dora_magma-0.1.0.dist-info/WHEEL
dora_magma-0.1.0.dist-info/entry_points.txt
dora_magma-0.1.0.dist-info/RECORD
